GoldyBot/__init__.py
GoldyBot/config.py
GoldyBot/errors.py
GoldyBot/info.py
GoldyBot/logging.py
GoldyBot/paths.py
GoldyBot/assets/ding.mp3
GoldyBot/assets/ding.wav
GoldyBot/assets/goldy.json
GoldyBot/assets/run.py
GoldyBot/assets/token.env
GoldyBot/cli/__init__.py
GoldyBot/cli/__main__.py
GoldyBot/cli/_setup.py
GoldyBot/cli/extensions.py
GoldyBot/cli/file_templates.py
GoldyBot/goldy/__init__.py
GoldyBot/goldy/goldy_config.py
GoldyBot/goldy/permission_system.py
GoldyBot/goldy/perms.py
GoldyBot/goldy/presence.py
GoldyBot/goldy/system.py
GoldyBot/goldy/token.py
GoldyBot/goldy/commands/__init__.py
GoldyBot/goldy/commands/command.py
GoldyBot/goldy/commands/decorator.py
GoldyBot/goldy/commands/group_command.py
GoldyBot/goldy/commands/listener.py
GoldyBot/goldy/commands/loader.py
GoldyBot/goldy/commands/prefix_command.py
GoldyBot/goldy/commands/slash_command.py
GoldyBot/goldy/database/__init__.py
GoldyBot/goldy/database/databases/__init__.py
GoldyBot/goldy/database/wrappers/__init__.py
GoldyBot/goldy/database/wrappers/guild.py
GoldyBot/goldy/database/wrappers/member.py
GoldyBot/goldy/events/__init__.py
GoldyBot/goldy/events/decorator.py
GoldyBot/goldy/events/event_types.py
GoldyBot/goldy/extensions/__init__.py
GoldyBot/goldy/extensions/extension_loader.py
GoldyBot/goldy/extensions/extension_metadata.py
GoldyBot/goldy/guilds/__init__.py
GoldyBot/goldy/guilds/guild.py
GoldyBot/goldy/live_console/__init__.py
GoldyBot/goldy/live_console/app.py
GoldyBot/goldy/nextcore_utils/__init__.py
GoldyBot/goldy/nextcore_utils/colours.py
GoldyBot/goldy/nextcore_utils/defer.py
GoldyBot/goldy/nextcore_utils/files.py
GoldyBot/goldy/nextcore_utils/front_end_errors.py
GoldyBot/goldy/nextcore_utils/channels/__init__.py
GoldyBot/goldy/nextcore_utils/channels/delete_channel.py
GoldyBot/goldy/nextcore_utils/channels/get_channel.py
GoldyBot/goldy/nextcore_utils/embeds/__init__.py
GoldyBot/goldy/nextcore_utils/embeds/embed.py
GoldyBot/goldy/nextcore_utils/guilds/__init__.py
GoldyBot-5.0.dev13.dist-info/LICENSE
GoldyBot-5.0.dev13.dist-info/METADATA
GoldyBot-5.0.dev13.dist-info/WHEEL
GoldyBot-5.0.dev13.dist-info/entry_points.txt
GoldyBot-5.0.dev13.dist-info/top_level.txt
GoldyBot-5.0.dev13.dist-info/RECORD
