Metadata-Version: 2.1
Name: GoldyBot
Version: 5.0.dev13
Summary: Yet another another rewrite of Goldy Bot, a discord bot framework for my own bots.
Author-email: Goldy <goldy@devgoldy.xyz>
License: GNU GENERAL PUBLIC LICENSE
Project-URL: GitHub, https://github.com/Goldy-Bot/Goldy-Bot-V5
Project-URL: BugTracker, https://github.com/Goldy-Bot/Goldy-Bot-V5/issues
Project-URL: ChangeLog, https://github.com/Goldy-Bot/Goldy-Bot-V5/master/CHANGELOG.md
Keywords: goldybot,goldy bot,Goldy Bot,Goldy Bot V4,Goldy Bot V3,goldy,Goldy Bot V5
Classifier: Operating System :: Microsoft :: Windows :: Windows 11
Classifier: Operating System :: Microsoft :: Windows :: Windows 10
Classifier: Operating System :: POSIX :: Linux
Classifier: License :: OSI Approved :: GNU General Public License v3 (GPLv3)
Classifier: Programming Language :: Python :: 3.8
Classifier: Programming Language :: Python :: 3.9
Classifier: Programming Language :: Python :: 3.10
Classifier: Programming Language :: Python :: 3.11
Requires-Python: >=3.8
License-File: LICENSE
Requires-Dist: requests
Requires-Dist: setuptools >=68.2.2
Requires-Dist: devgoldyutils >=2.5
Requires-Dist: nextcore[speed] >=2.0.1
Requires-Dist: click >=8.1.3
Requires-Dist: python-decouple >=3.7
Requires-Dist: motor
Requires-Dist: cmd2
Requires-Dist: regex
Requires-Dist: psutil
Requires-Dist: dateparser
Requires-Dist: toml
Requires-Dist: colorthief
Requires-Dist: get-annotations
Requires-Dist: packaging
Requires-Dist: importlib-metadata ; python_version < "3.8"
Provides-Extra: dev
Requires-Dist: Sphinx ; extra == 'dev'
Requires-Dist: sphinxext-opengraph ; extra == 'dev'
Requires-Dist: sphinx-inline-tabs ; extra == 'dev'
Requires-Dist: furo ; extra == 'dev'
Requires-Dist: myst-parser ; extra == 'dev'
Requires-Dist: sphinx-copybutton ; extra == 'dev'
Requires-Dist: pytest ; extra == 'dev'
Requires-Dist: pytest-cov ; extra == 'dev'
Requires-Dist: ruff ; extra == 'dev'
Requires-Dist: build ; extra == 'dev'
